croudtech_python_aws_lambda_helpers/__init__.py
croudtech_python_aws_lambda_helpers/cli.py
croudtech_python_aws_lambda_helpers/ssm_config.py
croudtech_python_aws_lambda_helpers-1.0.14.dist-info/AUTHORS.rst
croudtech_python_aws_lambda_helpers-1.0.14.dist-info/LICENSE.txt
croudtech_python_aws_lambda_helpers-1.0.14.dist-info/METADATA
croudtech_python_aws_lambda_helpers-1.0.14.dist-info/WHEEL
croudtech_python_aws_lambda_helpers-1.0.14.dist-info/entry_points.txt
croudtech_python_aws_lambda_helpers-1.0.14.dist-info/top_level.txt
croudtech_python_aws_lambda_helpers-1.0.14.dist-info/RECORD
