Metadata-Version: 2.1
Name: croudtech-python-aws-lambda-helpers
Version: 1.0.14
Summary: Add a short description here!
Home-page: https://github.com/pyscaffold/pyscaffold/
Author: Jim Robinson
Author-email: jscrobinson@gmail.com
License: mit
Project-URL: Documentation, https://pyscaffold.org/
Platform: any
Classifier: Development Status :: 4 - Beta
Classifier: Programming Language :: Python
Requires-Dist: boto3 (==1.16.28)
Requires-Dist: botocore (==1.19.28)
Requires-Dist: bson (==0.5.10)
Requires-Dist: click (==7.1.2)
Requires-Dist: loguru (==0.5.3)
Requires-Dist: pyaml (==20.4.0)
Requires-Dist: pyyaml (==5.3.1)
Requires-Dist: s3transfer (==0.3.3)
Requires-Dist: urllib3 (==1.26.2) ; python_version != "3.4"
Requires-Dist: jmespath (==0.10.0) ; python_version >= "2.6" and python_version not in "3.0, 3.1, 3.2, 3.3"
Requires-Dist: python-dateutil (==2.8.1) ; python_version >= "2.7" and python_version not in "3.0, 3.1, 3.2, 3.3"
Requires-Dist: six (==1.15.0) ; python_version >= "2.7" and python_version not in "3.0, 3.1, 3.2, 3.3"
